{"county": "lewis_clark", "date": "2026-04-28", "swe_index": 12.35, "percent_of_median": 61, "trend": "→", "status": "Below Normal", "forage_score": 57, "forage_model": {"sp": 58.0, "mi": 66.0, "vr": 55.0, "dc": 48.5, "lu": 50.0, "category": "Fair", "confidence": "High", "model": "HC Forage v2.1", "nass_week": "2026-04-26"}, "precip_ytd": {"inches": 29.5, "percent_of_median": 146, "status": "Above Normal"}, "drought": {"valid_end": "2026-04-27", "none_pct": 0.29, "d0_pct": 99.71, "d1_pct": 54.72, "d2_pct": 37.11, "d3_pct": 0.0, "d4_pct": 0.0, "worst_class": "D2"}, "streamflow": {"gauge_name": "Dearborn River near Craig", "site_no": "06073500", "cfs": 231.0, "percentile": 39, "status": "Normal"}, "soil_moisture": null, "precip_anomaly": {"month_end": "2026-03", "m1": {"inches": 2.76, "normal": 1.71, "anomaly": 1.05, "rank": 121}, "m3": {"inches": 5.04, "normal": 5.33, "anomaly": -0.29, "rank": 63}, "m12": {"inches": 22.07, "normal": 22.98, "anomaly": -0.91, "rank": 66}}}
