{"county": "stillwater", "date": "2026-05-05", "swe_index": 0.0, "percent_of_median": 0, "trend": "↓", "status": "No Snowpack", "forage_score": 42, "forage_model": {"sp": 65.0, "mi": 34.2, "vr": 40.0, "dc": 37.7, "lu": 50.0, "category": "Poor", "confidence": "Medium", "model": "HC Forage v2.1", "nass_week": "2026-05-03"}, "precip_ytd": null, "drought": {"valid_end": "2026-05-04", "none_pct": 0.0, "d0_pct": 100.0, "d1_pct": 89.57, "d2_pct": 50.59, "d3_pct": 0.0, "d4_pct": 0.0, "worst_class": "D2"}, "streamflow": {"gauge_name": "Stillwater River near Absarokee", "site_no": "06205000", "cfs": 426.0, "percentile": 17, "status": "Below Normal"}, "soil_moisture": {"shallow_vwc_pct": 20.5, "deep_vwc_pct": 26.0, "station_count": 9, "source": "Montana Mesonet"}, "precip_anomaly": null}
